{
	"_transient": null,
	"attributes": {
		"AT32_CEDULAVN889": {
			"attributeId": "AT32_CEDULAVN889",
			"autoGeneratedStr": "F",
			"columnName": null,
			"customizationLayer": 0,
			"customizationLayerDescription": "ECU",
			"dataType": "String",
			"entityPk": {
				"entityId": "EN_CLIENTEDF_889",
				"version": "1.0.0"
			},
			"expression": null,
			"falseValue": null,
			"labelId": null,
			"length": 0,
			"listValues": null,
			"name": "cedula",
			"objectType": null,
			"order": 1,
			"pkStr": "F",
			"requiredStr": "F",
			"transientStr": "F",
			"trueValue": null
		},
		"AT33_TELEFONO889": {
			"attributeId": "AT33_TELEFONO889",
			"autoGeneratedStr": "F",
			"columnName": null,
			"customizationLayer": 0,
			"customizationLayerDescription": "ECU",
			"dataType": "String",
			"entityPk": {
				"entityId": "EN_CLIENTEDF_889",
				"version": "1.0.0"
			},
			"expression": null,
			"falseValue": null,
			"labelId": null,
			"length": 0,
			"listValues": null,
			"name": "telefono",
			"objectType": null,
			"order": 5,
			"pkStr": "F",
			"requiredStr": "F",
			"transientStr": "F",
			"trueValue": null
		},
		"AT43_NOMBREKA889": {
			"attributeId": "AT43_NOMBREKA889",
			"autoGeneratedStr": "F",
			"columnName": null,
			"customizationLayer": 0,
			"customizationLayerDescription": "ECU",
			"dataType": "String",
			"entityPk": {
				"entityId": "EN_CLIENTEDF_889",
				"version": "1.0.0"
			},
			"expression": null,
			"falseValue": null,
			"labelId": null,
			"length": 0,
			"listValues": null,
			"name": "nombre",
			"objectType": null,
			"order": 2,
			"pkStr": "F",
			"requiredStr": "F",
			"transientStr": "F",
			"trueValue": null
		},
		"AT59_APELLIOO889": {
			"attributeId": "AT59_APELLIOO889",
			"autoGeneratedStr": "F",
			"columnName": null,
			"customizationLayer": 0,
			"customizationLayerDescription": "ECU",
			"dataType": "String",
			"entityPk": {
				"entityId": "EN_CLIENTEDF_889",
				"version": "1.0.0"
			},
			"expression": null,
			"falseValue": null,
			"labelId": null,
			"length": 0,
			"listValues": null,
			"name": "apellido",
			"objectType": null,
			"order": 3,
			"pkStr": "F",
			"requiredStr": "F",
			"transientStr": "F",
			"trueValue": null
		},
		"AT69_DIRECCIN889": {
			"attributeId": "AT69_DIRECCIN889",
			"autoGeneratedStr": "F",
			"columnName": null,
			"customizationLayer": 0,
			"customizationLayerDescription": "ECU",
			"dataType": "String",
			"entityPk": {
				"entityId": "EN_CLIENTEDF_889",
				"version": "1.0.0"
			},
			"expression": null,
			"falseValue": null,
			"labelId": null,
			"length": 0,
			"listValues": null,
			"name": "direccion",
			"objectType": null,
			"order": 4,
			"pkStr": "F",
			"requiredStr": "F",
			"transientStr": "F",
			"trueValue": null
		}
	},
	"customizationLayer": 0,
	"customizationLayerDescription": "ECU",
	"databaseName": null,
	"dbmsName": null,
	"description": null,
	"id": {
		"entityId": "EN_CLIENTEDF_889",
		"version": "1.0.0"
	},
	"isAutomatic": false,
	"isImported": false,
	"moduleId": "VNTAS",
	"name": {
		"$ref": "../../VNTAS/relations/componentKeys.json#/Entities/EN_CLIENTEDF_889/name"
	},
	"related": false,
	"tableName": null,
	"transient": null
}
